{
  "properties": {
    "propertyPack": {
      "properties": {
        "searches": {
          "items": {
            "oneOf": [
              null,
              {
                "properties": {
                  "results": {
                    "items": {
                      "oneOf": [
                        null,
                        null,
                        {
                          "properties": {
                            "drainageAndWater": {
                              "properties": {
                                "maps": {
                                  "con29DWRef": "1",
                                  "properties": {
                                    "publicSewerMapAttached": {
                                      "con29DWRef": "1.1"
                                    },
                                    "waterworksMapAttached": {
                                      "con29DWRef": "1.2"
                                    }
                                  }
                                },
                                "drainage": {
                                  "con29DWRef": "2",
                                  "properties": {
                                    "publicFoulDrainage": {
                                      "con29DWRef": "2.1"
                                    },
                                    "publicSurfaceDrainage": {
                                      "con29DWRef": "2.2"
                                    },
                                    "surfaceDrainageCharge": {
                                      "con29DWRef": "2.3"
                                    },
                                    "publicDrainWithinBoundaries": {
                                      "con29DWRef": "2.4"
                                    },
                                    "publicSewerWithin100ft": {
                                      "con29DWRef": "2.5"
                                    },
                                    "sewersSubjectOfAdoptionAgreement": {
                                      "con29DWRef": "2.6"
                                    },
                                    "sewerageUndertakerApproval": {
                                      "con29DWRef": "2.7"
                                    },
                                    "riskOfInternalFlooding": {
                                      "con29DWRef": "2.8"
                                    },
                                    "distanceToNearestSewerageTreatment": {
                                      "con29DWRef": "2.9"
                                    }
                                  }
                                },
                                "water": {
                                  "con29DWRef": "3",
                                  "properties": {
                                    "mainsWaterConnected": {
                                      "con29DWRef": "3.1"
                                    },
                                    "waterMainsWithinBoundaries": {
                                      "con29DWRef": "3.2"
                                    },
                                    "waterMainsSubjectOfAdoptionAgreement": {
                                      "con29DWRef": "3.3"
                                    },
                                    "lowWaterPressureRisk": {
                                      "con29DWRef": "3.4"
                                    },
                                    "waterQualityAnalysis": {
                                      "con29DWRef": "3.5"
                                    },
                                    "authorisedDeparturesFrom2000Regulations": {
                                      "con29DWRef": "3.6"
                                    },
                                    "waterMeterLocation": {
                                      "con29DWRef": "3.7"
                                    }
                                  }
                                },
                                "charging": {
                                  "con29DWRef": "4",
                                  "properties": {
                                    "sewerageProvider": {
                                      "con29DWRef": "4.1.1"
                                    },
                                    "waterProvider": {
                                      "con29DWRef": "4.1.2"
                                    },
                                    "sewerageBills": {
                                      "con29DWRef": "4.2"
                                    },
                                    "waterBills": {
                                      "con29DWRef": "4.3"
                                    },
                                    "currentChargingBasis": {
                                      "con29DWRef": "4.4"
                                    },
                                    "consequentialChargingBasis": {
                                      "con29DWRef": "4.5"
                                    }
                                  }
                                }
                              }
                            }
                          }
                        }
                      ]
                    }
                  }
                }
              }
            ]
          }
        }
      }
    }
  }
}